HISTORY.txt
LICENSE.txt
MANIFEST.in
README.txt
ceDataSource.py
ceDatabase.py
ceDatabaseCache.py
ceModuleLoader.py
ceWin32NamedPipes.py
cx_ClassLibrary.py
cx_DatabaseTable.py
cx_Exceptions.py
cx_Handles.py
cx_IniFile.py
cx_LoggingOptions.py
cx_OptionParser.py
cx_Parser.py
cx_ReadLine.py
cx_Settings.py
cx_ShellUtils.py
cx_Threads.py
cx_Tracing.py
cx_Utils.py
cx_Win32Pipe.py
cx_Win32Service.py
cx_XML.py
pyproject.toml
setup.cfg
setup.py
srml2pdf.py
xlml2xlsx.py
ceGUI/Application.py
ceGUI/Columns.py
ceGUI/CommonDialogs.py
ceGUI/CommonPanels.py
ceGUI/Config.py
ceGUI/ContainerControls.py
ceGUI/DataEditors.py
ceGUI/FilterArgs.py
ceGUI/Framework.py
ceGUI/GridControl.py
ceGUI/Images.py
ceGUI/ListControl.py
ceGUI/Menus.py
ceGUI/Reports.py
ceGUI/SimpleControls.py
ceGUI/TreeControl.py
ceGUI/__init__.py
cx_PyGenLib.egg-info/PKG-INFO
cx_PyGenLib.egg-info/SOURCES.txt
cx_PyGenLib.egg-info/dependency_links.txt
cx_PyGenLib.egg-info/top_level.txt