Metadata-Version: 1.2
Name: cx-PyGenLib
Version: 3.2
Summary: Set of general Python modules
Home-page: https://github.com/anthony-tuininga/cx_PyGenLib
Author: Anthony Tuininga
Author-email: anthony.tuininga@gmail.com
License: Python Software Foundation License
Platform: UNKNOWN
Requires-Python: >=3.6
